{
  "grid": "hexagonal",
  "width": 10,
  "height": 10,
  "wrapping": false,
  "tiles": [33,  9, 57, 41,  9,  8, 49,  8,  1, 56, 
             4,  2, 36, 36, 48,  2, 21, 24, 34,  4, 
            33,  9,  9, 12, 22,  5, 58,  2, 32, 52, 
            21,  9,  8, 35,  8, 34, 37,  8, 22,  4, 
            35,  9, 41, 40,  4, 32, 36,  5, 26, 32, 
            37,  8, 36,  5,  9, 44,  4,  3, 40, 20, 
            33, 13, 40, 37,  9, 40,  4, 17,  9, 14, 
            21, 40,  4,  4, 33, 44, 34, 17,  9, 24, 
            34, 48, 37, 41,  8,  4, 52,  6, 32, 50, 
             6,  4,  4,  4,  1, 10,  4,  1, 14,  4 ]
}