{
  "grid": "hexagonal",
  "width": 15,
  "height": 15,
  "wrap": false,
  "tiles": [33, 41,  9, 40, 17,  9,  9,  9, 40, 17,  8, 32, 17, 56, 48, 
            52,  5, 40, 39,  8,  1, 56,  1, 15, 40, 17, 14,  2, 22, 20, 
             2,  5,  8, 20, 52, 16, 18, 52, 32, 17, 14,  1, 57, 10, 50, 
            33, 40,  2, 18, 54, 34,  2, 21, 14, 48, 32,  2,  4,  2, 20, 
            33, 44,  4, 18, 18,  4, 52,  2,  1, 10,  5, 44,  1,  9, 42, 
            36, 36, 18, 35, 40,  2, 53,  8, 32, 33, 40,  5, 25, 25, 28, 
            33, 12,  7,  8,  4, 20, 18,  4, 32, 36,  4,  5, 10, 50,  2, 
            20, 16, 32, 32,  2,  2,  1, 25, 44, 36,  1, 25, 26, 21,  8, 
             3, 11,  8, 20, 21, 24,  1, 10,  1, 13, 13, 10, 50,  3, 24, 
            17,  9, 10,  2, 18,  1, 40, 32, 17, 25, 25, 10, 20, 19,  8, 
             3,  9, 40, 32, 34, 32, 32, 36,  6, 50,  2, 17, 26, 19, 40, 
             1, 24,  5, 28, 52,  5, 13, 13, 26, 20, 50,  2,  2, 17, 12, 
            33, 10, 16, 18, 34,  5, 40,  1, 10,  2, 18, 20, 49, 42, 16, 
            36, 18,  3, 25, 28, 17, 29, 24,  1, 10, 18, 34,  4,  6, 16, 
             1, 15,  9, 10,  2,  2,  2,  3,  9,  9, 10,  1, 13,  9, 10 ]
}