{
  "grid": "hexagonal",
  "width": 10,
  "height": 10,
  "wrap": false,
  "tiles": [ 1,  9, 40, 16, 48,  1, 56, 33,  9, 40, 
            16, 49, 15, 42,  4, 50,  4,  5, 24,  4, 
            34, 50,  5, 24, 36, 18,  4, 32, 35,  8, 
            22, 36, 35,  8,  7,  8, 16,  5, 29,  8, 
             3, 56,  4,  4, 17,  8, 34, 16,  3, 40, 
             2, 21,  9, 10, 17,  8, 22, 16, 17, 12, 
            32, 19,  8, 32, 18, 16, 19, 11, 10, 48, 
             7, 40,  1, 15, 26, 19, 40, 16, 34,  4, 
             1, 25, 60, 17, 10, 19, 24, 38, 49, 44, 
             2,  2,  7,  9, 10,  3,  8,  6,  4,  4 ]
}